modelbase/__init__.py
modelbase/core/__init__.py
modelbase/core/algebraicmixin.py
modelbase/core/basemodel.py
modelbase/core/compoundmixin.py
modelbase/core/parametermixin.py
modelbase/core/ratemixin.py
modelbase/core/stoichiometricmixin.py
modelbase/core/utils.py
modelbase/ode/__init__.py
modelbase/ode/integrators/__init__.py
modelbase/ode/integrators/abstract_integrator.py
modelbase/ode/integrators/int_assimulo.py
modelbase/ode/integrators/int_scipy.py
modelbase/ode/models/__init__.py
modelbase/ode/models/abstract_model.py
modelbase/ode/models/labelmodel.py
modelbase/ode/models/linearlabelmodel.py
modelbase/ode/models/model.py
modelbase/ode/simulators/__init__.py
modelbase/ode/simulators/abstract_simulator.py
modelbase/ode/simulators/labelsimulator.py
modelbase/ode/simulators/linearlabelsimulator.py
modelbase/ode/simulators/simulator.py
modelbase/ode/utils/__init__.py
modelbase/ode/utils/algebraicfunctions.py
modelbase/ode/utils/mca.py
modelbase/ode/utils/ratefunctions.py
modelbase/ode/utils/ratelaws.py
modelbase/py.typed
modelbase/sbml/__init__.py
modelbase/sbml/data.py
modelbase/sbml/mathml.py
modelbase/sbml/parser.py
modelbase/sbml/unit_conversion.py
modelbase/typing.py
modelbase/utils/__init__.py
modelbase/utils/plotting.py
modelbase-1.58.0.dist-info/LICENSE
modelbase-1.58.0.dist-info/WHEEL
modelbase-1.58.0.dist-info/METADATA
modelbase-1.58.0.dist-info/RECORD
