Metadata-Version: 2.1
Name: modelbase
Version: 1.58.0
Summary: A package to build metabolic models
Home-page: https://gitlab.com/qtb-hhu/modelbase-software
License: GPL-3.0-or-later
Keywords: modelling,ode,metabolic
Author: Marvin van Aalst
Author-email: marvin.vanaalst@gmail.com
Maintainer: Oliver Ebenhöh
Maintainer-email: oliver.ebenhoeh@hhu.de
Requires-Python: >=3.9,<3.13
Classifier: Development Status :: 5 - Production/Stable
Classifier: Environment :: Console
Classifier: Intended Audience :: Developers
Classifier: Intended Audience :: Science/Research
Classifier: License :: OSI Approved :: GNU General Public License v3 or later (GPLv3+)
Classifier: Operating System :: MacOS
Classifier: Operating System :: Microsoft :: Windows
Classifier: Operating System :: OS Independent
Classifier: Operating System :: POSIX
Classifier: Operating System :: Unix
Classifier: Programming Language :: Python :: 3
Classifier: Programming Language :: Python :: 3.9
Classifier: Programming Language :: Python :: 3.10
Classifier: Programming Language :: Python :: 3.11
Classifier: Programming Language :: Python :: 3
Classifier: Programming Language :: Python :: 3.10
Classifier: Programming Language :: Python :: 3.11
Classifier: Programming Language :: Python :: 3.9
Classifier: Topic :: Scientific/Engineering
Classifier: Topic :: Software Development
Requires-Dist: black (>=24.4)
Requires-Dist: ipywidgets (>=8.1)
Requires-Dist: matplotlib (>=3.9)
Requires-Dist: numpy (>=2.0)
Requires-Dist: pandas (>=2.2)
Requires-Dist: python-libsbml (>=5.20)
Requires-Dist: scipy (>=1.13)
Requires-Dist: sympy (>=1.12)
Requires-Dist: tqdm (>=4.66)
Requires-Dist: typing-extensions (>=4.12)
Project-URL: Documentation, https://modelbase.readthedocs.io/en/latest/
Project-URL: Repository, https://gitlab.com/qtb-hhu/modelbase-software
